cisco_nso_mcp_server/__init__.py
cisco_nso_mcp_server/server.py
cisco_nso_mcp_server/services/__init__.py
cisco_nso_mcp_server/services/devices.py
cisco_nso_mcp_server/services/environment.py
cisco_nso_mcp_server/services/services.py
cisco_nso_mcp_server/utils/__init__.py
cisco_nso_mcp_server/utils/loggerfactory.py
cisco_nso_mcp_server/utils/logging.py
cisco_nso_mcp_server-3.1.0.dist-info/METADATA
cisco_nso_mcp_server-3.1.0.dist-info/WHEEL
cisco_nso_mcp_server-3.1.0.dist-info/entry_points.txt
cisco_nso_mcp_server-3.1.0.dist-info/licenses/LICENSE
cisco_nso_mcp_server-3.1.0.dist-info/RECORD
