Metadata-Version: 2.4
Name: cisco-nso-mcp-server
Version: 3.1.0
Summary: Cisco NSO MCP Server
Project-URL: Homepage, https://github.com/dbono711/cisco-nso-mcp-server
Author-email: Darren Bono <dbono215@gmail.com>
License-Expression: MIT
License-File: LICENSE
Requires-Python: <4.0,>=3.12
Requires-Dist: cisco-nso-restconf>=1.0.5
Requires-Dist: fastmcp>=2.14.1
Requires-Dist: httpx>=0.28.1
Requires-Dist: python-dotenv>=1.2.1
